snowoptics/__init__.py
snowoptics/refractive_index.py
snowoptics/snowoptics.py
snowoptics-0.90.dist-info/LICENSE
snowoptics-0.90.dist-info/WHEEL
snowoptics-0.90.dist-info/METADATA
snowoptics-0.90.dist-info/RECORD
